dataclass_structor/__init__.py
dataclass_structor/structure.py
dataclass_structor/unstructure.py
dataclass_structor-0.0.6.dist-info/LICENSE
dataclass_structor-0.0.6.dist-info/WHEEL
dataclass_structor-0.0.6.dist-info/METADATA
dataclass_structor-0.0.6.dist-info/RECORD
