Metadata-Version: 2.1
Name: dataclass_structor
Version: 0.0.6
Summary: Typed object structure/destructure.
Home-page: https://github.com/hockeybuggy/dataclass_structor
License: UNKNOWN
Author: Douglas Anderson
Author-email: hockeybuggy@gmail.com
Requires-Python: >=3.7
Classifier: Intended Audience :: Developers
Classifier: License :: OSI Approved :: MIT License
Classifier: Programming Language :: Python :: 3.7
Project-URL: Documentation, https://dataclass-structor.readthedocs.io
